whad/__init__.py
whad/exceptions.py
whad/helpers.py
whad/version.py
whad/ble/__init__.py
whad/ble/crypto.py
whad/ble/exceptions.py
whad/ble/injecting.py
whad/ble/metadata.py
whad/ble/scanning.py
whad/ble/sniffing.py
whad/ble/cli/__init__.py
whad/ble/cli/ble_connect.py
whad/ble/cli/ble_proxy.py
whad/ble/cli/ble_spawn.py
whad/ble/cli/central/__init__.py
whad/ble/cli/central/cache.py
whad/ble/cli/central/helpers.py
whad/ble/cli/central/shell.py
whad/ble/cli/central/commands/__init__.py
whad/ble/cli/central/commands/emulate.py
whad/ble/cli/central/commands/profile.py
whad/ble/cli/central/commands/read.py
whad/ble/cli/central/commands/scan.py
whad/ble/cli/central/commands/shell.py
whad/ble/cli/central/commands/write.py
whad/ble/cli/clone/__init__.py
whad/ble/cli/peripheral/__init__.py
whad/ble/cli/peripheral/shell.py
whad/ble/cli/peripheral/commands/__init__.py
whad/ble/cli/peripheral/commands/shell.py
whad/ble/connector/__init__.py
whad/ble/connector/base.py
whad/ble/connector/central.py
whad/ble/connector/hijacker.py
whad/ble/connector/injector.py
whad/ble/connector/peripheral.py
whad/ble/connector/replay.py
whad/ble/connector/scanner.py
whad/ble/connector/sniffer.py
whad/ble/connector/translator.py
whad/ble/mock/__init__.py
whad/ble/mock/central.py
whad/ble/mock/device.py
whad/ble/mock/peripheral.py
whad/ble/mock/scan.py
whad/ble/mock/stack/__init__.py
whad/ble/mock/stack/attribute.py
whad/ble/mock/stack/client.py
whad/ble/mock/stack/find_info.py
whad/ble/mock/stack/l2cap.py
whad/ble/mock/stack/notif.py
whad/ble/mock/stack/procedure.py
whad/ble/mock/stack/read.py
whad/ble/mock/stack/read_by_group_type.py
whad/ble/mock/stack/read_by_type.py
whad/ble/mock/stack/readblob.py
whad/ble/mock/stack/server.py
whad/ble/mock/stack/write.py
whad/ble/mock/stack/writecmd.py
whad/ble/profile/__init__.py
whad/ble/profile/advdata.py
whad/ble/profile/attribute.py
whad/ble/profile/characteristic.py
whad/ble/profile/device.py
whad/ble/profile/service.py
whad-1.2.12.dist-info/licenses/LICENSE
whad-1.2.12.dist-info/METADATA
whad-1.2.12.dist-info/WHEEL
whad-1.2.12.dist-info/entry_points.txt
whad-1.2.12.dist-info/top_level.txt
whad-1.2.12.dist-info/RECORD
