Metadata-Version: 2.4
Name: whad
Version: 1.2.12
Summary: Wireless protocols hacking framework
Author: Damien CAUQUIL, Romain CAYRE
License: MIT License
Project-URL: Homepage, https://whad.io/
Project-URL: Documentation, https://whad.readthedocs.io/en/stable/
Project-URL: Issues, https://github.com/whad-team/whad-client/issues
Classifier: Programming Language :: Python :: 3
Classifier: Programming Language :: Python :: 3 :: Only
Classifier: Programming Language :: Python :: 3.9
Classifier: Programming Language :: Python :: 3.10
Classifier: Programming Language :: Python :: 3.11
Classifier: Programming Language :: Python :: 3.12
Classifier: Programming Language :: Python :: 3.13
Classifier: Operating System :: POSIX :: Linux
Requires-Python: <4,>=3.7
License-File: LICENSE
Requires-Dist: protobuf>=6.30
Requires-Dist: scapy~=2.6.1
Requires-Dist: pyserial~=3.5.0
Requires-Dist: pycryptodomex>=3.11.0
Requires-Dist: pyusb==1.2.1
Requires-Dist: cryptography>=36
Requires-Dist: prompt_toolkit~=3.0.48
Requires-Dist: hexdump~=3.3
Requires-Dist: pynput~=1.8.1
Requires-Dist: requests>=2.28.0
Requires-Dist: distro~=1.9
Requires-Dist: websockets>=11.0.3
Requires-Dist: packaging~=25.0
Requires-Dist: strenum~=0.4.15
Dynamic: license-file
